proyectoLeon/codigo/driver.v
task drv_init;
  begin

  	for (i=0;i<`c;i=i+1) begin
		L[i]=0;
	end

	for (i=0;i<`b;i=i+1) begin
		keyInBytes[i]=5+i;
	end

    @(negedge clk2) begin
		rst = 1;
    end 

    @(negedge clk2)
		rst = 0;

    @(negedge clk2)
		rst = 0;

  end

endtask

task drv_read;
	@(posedge clk2) begin
		L_sub_i = L[L_address];
		key_sub_i = keyInBytes[key_address];
	end
endtask

task drv_write;
	@(negedge clk2) begin
		L[L_address] = L_sub_i_prima;	
	end
endtask

proyectoLeon/codigo/keyExpansion.v
`timescale 1ns/10ps

module keyBytesToWords 
#(
	parameter b = 16,
	parameter b_length = 4,
	parameter w = 32,
	parameter u = 4,
	parameter c = 4,
	parameter c_length = 2
)

(
	input clk1,
	input clk2,
	input rst,
	input [7:0] key_sub_i,
	input [w-1:0] L_sub_i,
	output [b_length-1:0] key_address,
	output [c_length-1:0] L_address,
	output reg [w-1:0] L_sub_i_prima
);

	reg [b_length:0] count;

	wire done;


	assign done = (!count) ? 1:0;
	assign key_address = count;
	assign L_address = count/u;

	reg [w-1:0] temp;

	always @(posedge clk2 or posedge rst) begin

		if(rst) begin
			count = b;
		end

		else begin 
			if (done==0) begin
				temp = {L_sub_i[7:0],L_sub_i[w-1:0]};	
				//$display("L = %h   ,  temp = %h" , L_sub_i,temp);
				L_sub_i_prima = temp + key_sub_i;
			end
		end
	end

	always @(posedge clk1) begin
		if (done==0 && rst==0) begin
			count = count - 1;
		end
	end

endmodule
/*
module oper1 
#(
	parameter w = 32
)

(
	input clk,
	input rst,
	input [w-1:0] wordIn,
	input [7:0] constant,
	output reg [w-1:0] wordOut
);

	wire [w-9:0] zeros;
	assign zeros = 0;

	reg [7:0] temporal;

	always @(posedge clk or posedge rst) begin

		if(rst) begin
			wordOut = 0;
		end

		else begin
			temporal = #1 constant;
			wordOut = #1 {wordIn[7:0],wordIn[w-1:8]} + {zeros,temporal};	

		end

	end

endmodule
*/

proyectoLeon/codigo/testbench.v
`include "keyExpansion.v"
`timescale 1ns/10ps

`define w 32 // Cantidad de bits por palabra.
`define u 4 // Cantidad de bytes por palabra.
`define b 16 // Cantidad de bytes de la llave.
`define b_length 4 // Bits para direccionar a todos los bytes b de la llave.
`define t 26 // Cantidad de rondas.
`define c 4 // Tamaño del vector L. Corresponde a b/u.
`define c_length 2 // Cantidad de bits para direccionar al vector L.

module probador 
(
	output reg rst,
	output reg clk1,
	output reg clk2,
	output reg [8*`b-1:0] key,
	output reg [`w-1:0] L_sub_i,
	output reg [7:0] key_sub_i,
	input [`b_length-1:0] key_address,
	input [`c_length-1:0] L_address,
	input [`w-1:0] L_sub_i_prima
);

	integer i;

  	reg [`w-1:0] L [`c:0];
  	reg [7:0] keyInBytes [`b-1:0];

  	`include "driver.v"

	initial begin

    	$dumpfile("prueba.vcd");
		$dumpvars;
		
		key = 128'hFFFEEEE58684FFF05FFE493853000434;
		clk1 = 0;

		drv_init();

		repeat(20) begin
			fork 
				drv_write();
				drv_read();
			join
		end

		/*
		for (i=0;i<`c;i=i+1) begin
			L[i]=0;
		end

		key = 128'hFFFEEEE58684FFF05FFE493853000434;

		for (i=0;i<`b;i=i+1) begin
			keyInBytes[i]=5+i;
		end
		clk1 = 0;

    	rst = 0;
    	#3 rst = 1;
    	#1 rst = 0;
    	*/


		#2 $finish;
		
	end

	always #5 clk1 = ~clk1;	

	always @(*) begin
  		clk2 = #0.5 clk1;
  	end

  	/*
	always @(posedge clk2) begin
		L_sub_i = L[L_address];
		key_sub_i = keyInBytes[key_address];
	end

	always @(negedge clk2) begin
		L[L_address] = L_sub_i_prima;	
	end
	*/

endmodule


module tester;

  wire [7:0] key_sub_i;
  wire [`w-1:0] L_sub_i,L_sub_i_prima;
  wire [`b_length-1:0] key_address;
  wire [`c_length-1:0] L_address;
 
  probador test
  (
  	.clk1(clk1),
  	.clk2(clk2),
  	.rst(rst),
  	.key_sub_i(key_sub_i),
  	.L_sub_i(L_sub_i),
  	.L_sub_i_prima(L_sub_i_prima),
  	.key_address(key_address),
  	.L_address(L_address)
  );
  
  keyBytesToWords  
  #(
  	.b(`b),
  	.b_length(`b_length),
  	.w(`w),
  	.u(`u),
  	.c(`c),
  	.c_length(`c_length)
  )
  pegado 
  (
  	.clk1(clk1),
  	.clk2(clk2),
  	.rst(rst),
  	.key_sub_i(key_sub_i),
  	.L_sub_i(L_sub_i),
  	.L_sub_i_prima(L_sub_i_prima),
  	.key_address(key_address),
  	.L_address(L_address)
   );

endmodule

proyectoLeon/codigo/prueba.vcd
$date
	Fri Oct 23 18:03:01 2015
$end
$version
	Icarus Verilog
$end
$timescale
	10ps
$end
$scope module tester $end
$var wire 2 ! L_address [1:0] $end
$var wire 32 " L_sub_i [31:0] $end
$var wire 32 # L_sub_i_prima [31:0] $end
$var wire 1 $ clk1 $end
$var wire 1 % clk2 $end
$var wire 4 & key_address [3:0] $end
$var wire 8 ' key_sub_i [7:0] $end
$var wire 1 ( rst $end
$scope module test $end
$var wire 2 ) L_address [1:0] $end
$var wire 32 * L_sub_i_prima [31:0] $end
$var wire 4 + key_address [3:0] $end
$var reg 32 , L_sub_i [31:0] $end
$var reg 1 - clk1 $end
$var reg 1 . clk2 $end
$var integer 32 / i [31:0] $end
$var reg 128 0 key [127:0] $end
$var reg 8 1 key_sub_i [7:0] $end
$var reg 1 2 rst $end
$scope task drv_init $end
$upscope $end
$scope task drv_read $end
$upscope $end
$scope task drv_write $end
$upscope $end
$upscope $end
$scope module pegado $end
$var wire 2 3 L_address [1:0] $end
$var wire 32 4 L_sub_i [31:0] $end
$var wire 1 $ clk1 $end
$var wire 1 % clk2 $end
$var wire 1 5 done $end
$var wire 4 6 key_address [3:0] $end
$var wire 8 7 key_sub_i [7:0] $end
$var wire 1 ( rst $end
$var reg 32 8 L_sub_i_prima [31:0] $end
$var reg 5 9 count [4:0] $end
$var reg 32 : temp [31:0] $end
$upscope $end
$upscope $end
$enddefinitions $end
#0
$dumpvars
bx :
bx 9
bx 8
bx 7
bx 6
x5
bx 4
bx 3
x2
bx 1
b11111111111111101110111011100101100001101000010011111111111100000101111111111110010010010011100001010011000000000000010000110100 0
b10000 /
x.
0-
bx ,
bx +
bx *
bx )
x(
bx '
bx &
x%
0$
bx #
bx "
bx !
$end
#50
05
b0 &
b0 +
b0 6
b0 !
b0 )
b0 3
b10000 9
12
1(
0.
0%
#500
1-
1$
#550
1.
1%
#1000
0-
0$
#1050
02
0(
0.
0%
#1500
b1111 &
b1111 +
b1111 6
b11 !
b11 )
b11 3
b1111 9
1-
1$
#1550
1.
1%
#2000
0-
0$
#2050
0.
0%
#2500
b1110 &
b1110 +
b1110 6
b1110 9
1-
1$
#2550
b10011 8
b10011 #
b10011 *
b0 :
b10011 1
b10011 '
b10011 7
b0 ,
b0 "
b0 4
1.
1%
#3000
0-
0$
#3050
0.
0%
#3500
b1101 &
b1101 +
b1101 6
b1101 9
1-
1$
#3550
b100101 8
b100101 #
b100101 *
b10011 :
b10010 1
b10010 '
b10010 7
b10011 ,
b10011 "
b10011 4
1.
1%
#4000
0-
0$
#4050
0.
0%
#4500
b1100 &
b1100 +
b1100 6
b1100 9
1-
1$
#4550
b110110 8
b110110 #
b110110 *
b100101 :
b10001 1
b10001 '
b10001 7
b100101 ,
b100101 "
b100101 4
1.
1%
#5000
0-
0$
#5050
0.
0%
#5500
b1011 &
b1011 +
b1011 6
b10 !
b10 )
b10 3
b1011 9
1-
1$
#5550
b10000 8
b10000 #
b10000 *
b0 :
b10000 1
b10000 '
b10000 7
b0 ,
b0 "
b0 4
1.
1%
#6000
0-
0$
#6050
0.
0%
#6500
b1010 &
b1010 +
b1010 6
b1010 9
1-
1$
#6550
b11111 8
b11111 #
b11111 *
b10000 :
b1111 1
b1111 '
b1111 7
b10000 ,
b10000 "
b10000 4
1.
1%
#7000
0-
0$
#7050
0.
0%
#7500
b1001 &
b1001 +
b1001 6
b1001 9
1-
1$
#7550
b101101 8
b101101 #
b101101 *
b11111 :
b1110 1
b1110 '
b1110 7
b11111 ,
b11111 "
b11111 4
1.
1%
#8000
0-
0$
#8050
0.
0%
#8500
b1000 &
b1000 +
b1000 6
b1000 9
1-
1$
#8550
b111010 8
b111010 #
b111010 *
b101101 :
b1101 1
b1101 '
b1101 7
b101101 ,
b101101 "
b101101 4
1.
1%
#9000
0-
0$
#9050
0.
0%
#9500
b111 &
b111 +
b111 6
b1 !
b1 )
b1 3
b111 9
1-
1$
#9550
b1100 8
b1100 #
b1100 *
b0 :
b1100 1
b1100 '
b1100 7
b0 ,
b0 "
b0 4
1.
1%
#10000
0-
0$
#10050
0.
0%
#10500
b110 &
b110 +
b110 6
b110 9
1-
1$
#10550
b10111 8
b10111 #
b10111 *
b1100 :
b1011 1
b1011 '
b1011 7
b1100 ,
b1100 "
b1100 4
1.
1%
#11000
0-
0$
#11050
0.
0%
#11500
b101 &
b101 +
b101 6
b101 9
1-
1$
#11550
b100001 8
b100001 #
b100001 *
b10111 :
b1010 1
b1010 '
b1010 7
b10111 ,
b10111 "
b10111 4
1.
1%
#12000
0-
0$
#12050
0.
0%
#12500
b100 &
b100 +
b100 6
b100 9
1-
1$
#12550
b101010 8
b101010 #
b101010 *
b100001 :
b1001 1
b1001 '
b1001 7
b100001 ,
b100001 "
b100001 4
1.
1%
#13000
0-
0$
#13050
0.
0%
#13500
b11 &
b11 +
b11 6
b0 !
b0 )
b0 3
b11 9
1-
1$
#13550
b1000 8
b1000 #
b1000 *
b0 :
b1000 1
b1000 '
b1000 7
b0 ,
b0 "
b0 4
1.
1%
#14000
0-
0$
#14050
0.
0%
#14500
b10 &
b10 +
b10 6
b10 9
1-
1$
#14550
b1111 8
b1111 #
b1111 *
b1000 :
b111 1
b111 '
b111 7
b1000 ,
b1000 "
b1000 4
1.
1%
#15000
0-
0$
#15050
0.
0%
#15500
b1 &
b1 +
b1 6
b1 9
1-
1$
#15550
b10101 8
b10101 #
b10101 *
b1111 :
b110 1
b110 '
b110 7
b1111 ,
b1111 "
b1111 4
1.
1%
#16000
0-
0$
#16050
0.
0%
#16500
15
b0 &
b0 +
b0 6
b0 9
1-
1$
#16550
b101 1
b101 '
b101 7
b10101 ,
b10101 "
b10101 4
1.
1%
