proyectoLeon/codigo/keyExpansion.v
`timescale 1ns/10ps

module keyBytesToWords 
#(
	parameter b = 16, 
	parameter t = 26, 
	parameter w = 32,
	parameter u = 4,
	parameter c = 4
)

(
	input clk,
	input rst,
	input [w-1:0] pW,
	input [w-1:0] qW,
	input [8*b-1:0] key,
	output [w-1:0] out0,out1,out2,out3
);


	wire [w-1:0] S [t-1:0];
	reg [w-1:0] L [c-1:0];
	reg [w-1:0] temp;
	
	reg [4:0] count;
	wire done;


	assign done = (!count) ? 1:0;

	always @(posedge clk or posedge rst) begin

		if(rst) begin

			count = b;
			L[0] = 0;
			L[1] = 0;
			L[2] = 0;
			L[3] = 0;

		end

		else begin 
			if (done==0) begin
				temp = {L[(count)/u][7:0],L[(count)/u][w-1:0]};
				L[(count)/u] =  temp + qW;
				count = count - 1;
			end
		end
	end

	assign out0 = L[0];
	assign out1 = L[1];
	assign out2 = L[2];
	assign out3 = L[3];

endmodule
/*
module oper1 
#(
	parameter w = 32
)

(
	input clk,
	input rst,
	input [w-1:0] wordIn,
	input [7:0] constant,
	output reg [w-1:0] wordOut
);

	wire [w-9:0] zeros;
	assign zeros = 0;

	reg [7:0] temporal;

	always @(posedge clk or posedge rst) begin

		if(rst) begin
			wordOut = 0;
		end

		else begin
			temporal = #1 constant;
			wordOut = #1 {wordIn[7:0],wordIn[w-1:8]} + {zeros,temporal};	

		end

	end

endmodule
*/

proyectoLeon/codigo/testbench.v
`include "keyExpansion.v"
`timescale 1ns/10ps

`define w 32
`define b 16
`define t 26
`define c 4

// PROBADOR DEL PIPELINE IF_ID LISTOS.
module probador (clk,rst,pW,qW,key);
  
  
	// Salidas
  output reg [`w-1:0] pW;
  output reg [`w-1:0] qW;
  output reg [8*`b-1:0] key;
  output reg rst,clk;
 
	// Entradas.
	

	initial begin
	
    	$dumpfile("prueba.vcd");
		$dumpvars;
		
		clk = 0;
    	pW = 10;
    	qW = 5;
    	key = 128'hFFFEEEE58684FFF05FFE493853000434;
    	rst = 0;
    	#2 rst = 1;
    	#2 rst = 0;
		#170 $finish;
		
	end

	always #5 clk = ~clk;
	
endmodule


module tester;

  wire [`w-1:0] pW,Qw;
  wire [8*`b-1:0] key;
  wire [`w-1:0] out0,out1,out2,out3;

  probador test(clk,rst,pW,Qw,key);
  keyBytesToWords pegado (clk,rst,pW,Qw,key,out0,out1,out2,out3);

endmodule

proyectoLeon/codigo/prueba.vcd
$date
	Wed Oct 21 18:10:30 2015
$end
$version
	Icarus Verilog
$end
$timescale
	10ps
$end
$scope module tester $end
$var wire 32 ! Qw [31:0] $end
$var wire 1 " clk $end
$var wire 128 # key [127:0] $end
$var wire 32 $ out0 [31:0] $end
$var wire 32 % out1 [31:0] $end
$var wire 32 & out2 [31:0] $end
$var wire 32 ' out3 [31:0] $end
$var wire 32 ( pW [31:0] $end
$var wire 1 ) rst $end
$scope module test $end
$var reg 1 * clk $end
$var reg 128 + key [127:0] $end
$var reg 32 , pW [31:0] $end
$var reg 32 - qW [31:0] $end
$var reg 1 . rst $end
$upscope $end
$scope module pegado $end
$var wire 1 " clk $end
$var wire 1 / done $end
$var wire 128 0 key [127:0] $end
$var wire 32 1 out0 [31:0] $end
$var wire 32 2 out1 [31:0] $end
$var wire 32 3 out2 [31:0] $end
$var wire 32 4 out3 [31:0] $end
$var wire 32 5 pW [31:0] $end
$var wire 32 6 qW [31:0] $end
$var wire 1 ) rst $end
$var reg 5 7 count [4:0] $end
$var reg 32 8 temp [31:0] $end
$upscope $end
$upscope $end
$enddefinitions $end
#0
$dumpvars
bx 8
bx 7
b101 6
b1010 5
bz 4
bz 3
bz 2
bz 1
b11111111111111101110111011100101100001101000010011111111111100000101111111111110010010010011100001010011000000000000010000110100 0
x/
0.
b101 -
b1010 ,
b11111111111111101110111011100101100001101000010011111111111100000101111111111110010010010011100001010011000000000000010000110100 +
0*
0)
b1010 (
bz '
bz &
bz %
bz $
b11111111111111101110111011100101100001101000010011111111111100000101111111111110010010010011100001010011000000000000010000110100 #
0"
b101 !
$end
#200
0/
b0 '
b0 4
b0 &
b0 3
b0 %
b0 2
b0 $
b0 1
b10000 7
1.
1)
#400
0.
0)
#500
b1111 7
1*
1"
#1000
0*
0"
#1500
b1110 7
b101 '
b101 4
b0 8
1*
1"
#2000
0*
0"
#2500
b1101 7
b1010 '
b1010 4
b101 8
1*
1"
#3000
0*
0"
#3500
b1100 7
b1111 '
b1111 4
b1010 8
1*
1"
#4000
0*
0"
#4500
b1011 7
b10100 '
b10100 4
b1111 8
1*
1"
#5000
0*
0"
#5500
b1010 7
b101 &
b101 3
b0 8
1*
1"
#6000
0*
0"
#6500
b1001 7
b1010 &
b1010 3
b101 8
1*
1"
#7000
0*
0"
#7500
b1000 7
b1111 &
b1111 3
b1010 8
1*
1"
#8000
0*
0"
#8500
b111 7
b10100 &
b10100 3
b1111 8
1*
1"
#9000
0*
0"
#9500
b110 7
b101 %
b101 2
b0 8
1*
1"
#10000
0*
0"
#10500
b101 7
b1010 %
b1010 2
b101 8
1*
1"
#11000
0*
0"
#11500
b100 7
b1111 %
b1111 2
b1010 8
1*
1"
#12000
0*
0"
#12500
b11 7
b10100 %
b10100 2
b1111 8
1*
1"
#13000
0*
0"
#13500
b10 7
b101 $
b101 1
b0 8
1*
1"
#14000
0*
0"
#14500
b1 7
b1010 $
b1010 1
b101 8
1*
1"
#15000
0*
0"
#15500
1/
b0 7
b1111 $
b1111 1
b1010 8
1*
1"
