proyectoLeon/codigo/S_driver.v
task drv_init;
  begin

    @(negedge clk2) begin
		rst = 1;
    end 

    @(negedge clk2)
		rst = 0;

  end

endtask

task drv_read;
	@(posedge clk2) begin
		S_sub_i = S[S_address];
	end
endtask

task drv_write;
	@(negedge clk2) begin
		S[S_address+1] = S_sub_i_prima;	
	end
endtask

proyectoLeon/codigo/S_operation.v
`timescale 1ns/10ps


module initArrayS
#(
	parameter b = 16,
	parameter b_length = 4,
	parameter w = 32,
	parameter t = 26,
	parameter t_length = $clog2(t),
	parameter qW = 32'h9E3779B9
)

(
	input clk1,
	input clk2,
	input rst,
	input [w-1:0]S_sub_i,

	output reg [w-1:0] S_sub_i_prima,
	output [t_length-1:0] S_address,
	output wire done
);

	reg [t_length-1:0] count;
	assign S_address = count;

	assign done = (count==(t-1)) ? 1:0;

	always @(posedge clk2 or posedge rst) begin

		if(rst) begin
			count = 2**t_length-1;
		end

		else begin 
			if (done==0) begin
				S_sub_i_prima = S_sub_i + qW;
			end
		end
	end

	always @(posedge clk1) begin
		if (done==0 && rst==0) begin
			count = count + 1;
		end
	end


endmodule

proyectoLeon/codigo/S_tb.v
`include "S_operation.v"
`timescale 1ns/10ps

`define w 32 // Cantidad de bits por palabra.
`define u 4 // Cantidad de bytes por palabra.
`define b 16 // Cantidad de bytes de la llave.
`define b_length $clog2(`b) // Bits para direccionar a todos los bytes b de la llave.
`define r 12 // Cantidad de rondas.
`define t 2*(`r+1) // Tamaño del vector S es igual a 2 (r+1) donde r es la cantidad de rondas.
`define t_length $clog2(`t)
`define c 4 // Tamaño del vector L. Corresponde a b/u.
`define c_length 2 // Cantidad de bits para direccionar al vector L.
`define qW 5 //32'h9E3779B9 // Constantes
`define pW 10 //32'hB7E15163 //

module probador 
(
    output reg rst,
    output reg clk1,
    output reg clk2,
    output reg [`w-1:0] S_sub_i,
    input [`t_length-1:0] S_address,
    input [`w-1:0] S_sub_i_prima,
    input done
);

    // Definiciones iniciales
    integer i;

    reg [`w-1:0] S [`t-1:0];


    // Include del driver
    `include "S_driver.v"


    // Initial
    initial begin

    $dumpfile("S_prueba.vcd");
    $dumpvars;

    S[0] = `pW;
    clk1 = 0;

    // Tarea de inicio.
    drv_init();

    // Tareas para llenar el vector L.
    repeat(40) begin
        fork 
            drv_write();
            drv_read();
        join
    end

    // Finaliza la simulacion.
    #2 $finish;
    		
    end

    // Reloj 1.
    always #5 clk1 = ~clk1;	

    // Reloj 2, retrasado respecto al clk1.
    always @(*) begin
        clk2 = #0.5 clk1;
    end

endmodule




module tester;

    wire clk1;
    wire clk2;
    wire rst;
    wire [`w-1:0] S_sub_i;
    wire [`w-1:0] S_sub_i_prima;
    wire [`t_length-1:0] S_address;
    wire done;
     
    probador test
    (
        .clk1(clk1),
        .clk2(clk2),
        .rst(rst),
        .S_sub_i(S_sub_i),
        .S_sub_i_prima(S_sub_i_prima),
        .S_address(S_address),
        .done(done)
    );
      
    initArrayS
    #(
        .b(`b),
        .b_length(`b_length),
        .w(`w),
        .t(`t),
        .t_length(`t_length),
        .qW(`qW)
    )
    pegado 
    (
        .clk1(clk1),
        .clk2(clk2),
        .rst(rst),
        .S_sub_i(S_sub_i),
        .S_sub_i_prima(S_sub_i_prima),
        .S_address(S_address),
        .done(done)
    );

endmodule

proyectoLeon/codigo/S_prueba.vcd
$date
	Sun Oct 25 13:23:08 2015
$end
$version
	Icarus Verilog
$end
$timescale
	10ps
$end
$scope module tester $end
$var wire 5 ! S_address [4:0] $end
$var wire 32 " S_sub_i [31:0] $end
$var wire 32 # S_sub_i_prima [31:0] $end
$var wire 1 $ clk1 $end
$var wire 1 % clk2 $end
$var wire 1 & done $end
$var wire 1 ' rst $end
$scope module test $end
$var wire 5 ( S_address [4:0] $end
$var wire 32 ) S_sub_i_prima [31:0] $end
$var wire 1 & done $end
$var reg 32 * S_sub_i [31:0] $end
$var reg 1 + clk1 $end
$var reg 1 , clk2 $end
$var reg 1 - rst $end
$scope task drv_init $end
$upscope $end
$scope task drv_read $end
$upscope $end
$scope task drv_write $end
$upscope $end
$upscope $end
$scope module pegado $end
$var wire 5 . S_address [4:0] $end
$var wire 32 / S_sub_i [31:0] $end
$var wire 1 $ clk1 $end
$var wire 1 % clk2 $end
$var wire 1 & done $end
$var wire 1 ' rst $end
$var reg 32 0 S_sub_i_prima [31:0] $end
$var reg 5 1 count [4:0] $end
$upscope $end
$upscope $end
$enddefinitions $end
#0
$dumpvars
bx 1
bx 0
bx /
bx .
x-
x,
0+
bx *
bx )
bx (
x'
x&
x%
0$
bx #
bx "
bx !
$end
#50
0&
b11111 1
b11111 !
b11111 (
b11111 .
1-
1'
0,
0%
#500
1+
1$
#550
1,
1%
#1000
0+
0$
#1050
0-
0'
0,
0%
#1500
b0 1
b0 !
b0 (
b0 .
1+
1$
#1550
b1111 0
b1111 #
b1111 )
b1010 *
b1010 "
b1010 /
1,
1%
#2000
0+
0$
#2050
0,
0%
#2500
b1 1
b1 !
b1 (
b1 .
1+
1$
#2550
b10100 0
b10100 #
b10100 )
b1111 *
b1111 "
b1111 /
1,
1%
#3000
0+
0$
#3050
0,
0%
#3500
b10 1
b10 !
b10 (
b10 .
1+
1$
#3550
b11001 0
b11001 #
b11001 )
b10100 *
b10100 "
b10100 /
1,
1%
#4000
0+
0$
#4050
0,
0%
#4500
b11 1
b11 !
b11 (
b11 .
1+
1$
#4550
b11110 0
b11110 #
b11110 )
b11001 *
b11001 "
b11001 /
1,
1%
#5000
0+
0$
#5050
0,
0%
#5500
b100 1
b100 !
b100 (
b100 .
1+
1$
#5550
b100011 0
b100011 #
b100011 )
b11110 *
b11110 "
b11110 /
1,
1%
#6000
0+
0$
#6050
0,
0%
#6500
b101 1
b101 !
b101 (
b101 .
1+
1$
#6550
b101000 0
b101000 #
b101000 )
b100011 *
b100011 "
b100011 /
1,
1%
#7000
0+
0$
#7050
0,
0%
#7500
b110 1
b110 !
b110 (
b110 .
1+
1$
#7550
b101101 0
b101101 #
b101101 )
b101000 *
b101000 "
b101000 /
1,
1%
#8000
0+
0$
#8050
0,
0%
#8500
b111 1
b111 !
b111 (
b111 .
1+
1$
#8550
b110010 0
b110010 #
b110010 )
b101101 *
b101101 "
b101101 /
1,
1%
#9000
0+
0$
#9050
0,
0%
#9500
b1000 1
b1000 !
b1000 (
b1000 .
1+
1$
#9550
b110111 0
b110111 #
b110111 )
b110010 *
b110010 "
b110010 /
1,
1%
#10000
0+
0$
#10050
0,
0%
#10500
b1001 1
b1001 !
b1001 (
b1001 .
1+
1$
#10550
b111100 0
b111100 #
b111100 )
b110111 *
b110111 "
b110111 /
1,
1%
#11000
0+
0$
#11050
0,
0%
#11500
b1010 1
b1010 !
b1010 (
b1010 .
1+
1$
#11550
b1000001 0
b1000001 #
b1000001 )
b111100 *
b111100 "
b111100 /
1,
1%
#12000
0+
0$
#12050
0,
0%
#12500
b1011 1
b1011 !
b1011 (
b1011 .
1+
1$
#12550
b1000110 0
b1000110 #
b1000110 )
b1000001 *
b1000001 "
b1000001 /
1,
1%
#13000
0+
0$
#13050
0,
0%
#13500
b1100 1
b1100 !
b1100 (
b1100 .
1+
1$
#13550
b1001011 0
b1001011 #
b1001011 )
b1000110 *
b1000110 "
b1000110 /
1,
1%
#14000
0+
0$
#14050
0,
0%
#14500
b1101 1
b1101 !
b1101 (
b1101 .
1+
1$
#14550
b1010000 0
b1010000 #
b1010000 )
b1001011 *
b1001011 "
b1001011 /
1,
1%
#15000
0+
0$
#15050
0,
0%
#15500
b1110 1
b1110 !
b1110 (
b1110 .
1+
1$
#15550
b1010101 0
b1010101 #
b1010101 )
b1010000 *
b1010000 "
b1010000 /
1,
1%
#16000
0+
0$
#16050
0,
0%
#16500
b1111 1
b1111 !
b1111 (
b1111 .
1+
1$
#16550
b1011010 0
b1011010 #
b1011010 )
b1010101 *
b1010101 "
b1010101 /
1,
1%
#17000
0+
0$
#17050
0,
0%
#17500
b10000 1
b10000 !
b10000 (
b10000 .
1+
1$
#17550
b1011111 0
b1011111 #
b1011111 )
b1011010 *
b1011010 "
b1011010 /
1,
1%
#18000
0+
0$
#18050
0,
0%
#18500
b10001 1
b10001 !
b10001 (
b10001 .
1+
1$
#18550
b1100100 0
b1100100 #
b1100100 )
b1011111 *
b1011111 "
b1011111 /
1,
1%
#19000
0+
0$
#19050
0,
0%
#19500
b10010 1
b10010 !
b10010 (
b10010 .
1+
1$
#19550
b1101001 0
b1101001 #
b1101001 )
b1100100 *
b1100100 "
b1100100 /
1,
1%
#20000
0+
0$
#20050
0,
0%
#20500
b10011 1
b10011 !
b10011 (
b10011 .
1+
1$
#20550
b1101110 0
b1101110 #
b1101110 )
b1101001 *
b1101001 "
b1101001 /
1,
1%
#21000
0+
0$
#21050
0,
0%
#21500
b10100 1
b10100 !
b10100 (
b10100 .
1+
1$
#21550
b1110011 0
b1110011 #
b1110011 )
b1101110 *
b1101110 "
b1101110 /
1,
1%
#22000
0+
0$
#22050
0,
0%
#22500
b10101 1
b10101 !
b10101 (
b10101 .
1+
1$
#22550
b1111000 0
b1111000 #
b1111000 )
b1110011 *
b1110011 "
b1110011 /
1,
1%
#23000
0+
0$
#23050
0,
0%
#23500
b10110 1
b10110 !
b10110 (
b10110 .
1+
1$
#23550
b1111101 0
b1111101 #
b1111101 )
b1111000 *
b1111000 "
b1111000 /
1,
1%
#24000
0+
0$
#24050
0,
0%
#24500
b10111 1
b10111 !
b10111 (
b10111 .
1+
1$
#24550
b10000010 0
b10000010 #
b10000010 )
b1111101 *
b1111101 "
b1111101 /
1,
1%
#25000
0+
0$
#25050
0,
0%
#25500
b11000 1
b11000 !
b11000 (
b11000 .
1+
1$
#25550
b10000111 0
b10000111 #
b10000111 )
b10000010 *
b10000010 "
b10000010 /
1,
1%
#26000
0+
0$
#26050
0,
0%
#26500
1&
b11001 1
b11001 !
b11001 (
b11001 .
1+
1$
#26550
b10000111 *
b10000111 "
b10000111 /
1,
1%
