proyectoLeon/codigo/tea/version3/decipher.v
`timescale 1ns/10ps

`define IDLE 4'd0
`define SHIFT_V0_ADD_K2 4'd1
`define ADD_V0_SUM 4'd2
`define SHIFT_V0_ADD_K3 4'd3
`define XOR_ALL1 4'd4
`define SUB_ALL1 4'd5
`define SHIFT_V1_ADD_K0 4'd6
`define ADD_V1_SUM 4'd7
`define SHIFT_V1_ADD_K1 4'd8
`define XOR_ALL2 4'd9
`define SUB_ALL2 4'd10
`define SUB_DELTA 4'd11
`define DONE 4'd12

module decipher 
#(
	parameter WORD_SIZE = 32,
	parameter DELTA = 32'h9e3779b9,
	parameter ROUND_NUMBER = 32
)

(
	input wire clk,
	input wire rst,
	input wire iStart,
	// Texto plano
	input wire [WORD_SIZE-1:0] iV0,
	input wire [WORD_SIZE-1:0] iV1,
	// Llave
	input wire [WORD_SIZE-1:0] iK0,
	input wire [WORD_SIZE-1:0] iK1,
	input wire [WORD_SIZE-1:0] iK2,
	input wire [WORD_SIZE-1:0] iK3,
	// Texto cifrado
	output reg [WORD_SIZE-1:0] oC0,
	output reg [WORD_SIZE-1:0] oC1,
	output reg oDone
);

	parameter ROUND_NUMBER_BITS = $clog2(ROUND_NUMBER);

	reg [3:0] state;
	//
	reg [WORD_SIZE-1:0] rAux1;
	reg [WORD_SIZE-1:0] rAux2;
	reg [WORD_SIZE-1:0] rAux3;
	reg [WORD_SIZE-1:0] sum;
	reg [ROUND_NUMBER_BITS-1:0] rCount;
	//
	reg [WORD_SIZE-1:0] rAux1_nxt;
	reg [WORD_SIZE-1:0] rAux2_nxt;
	reg [WORD_SIZE-1:0] rAux3_nxt;
	reg [WORD_SIZE-1:0] sum_nxt;
	reg [ROUND_NUMBER_BITS-1:0] rCount_nxt;
	//
	reg [WORD_SIZE-1:0] oC0_nxt;
	reg [WORD_SIZE-1:0] oC1_nxt;
	reg oDone_nxt;


	// COMBINATIONAL LOGIC
	always@(*) begin

		rAux1_nxt = rAux1;
		rAux2_nxt = rAux2;
		rAux3_nxt = rAux3;
		oC0_nxt = oC0;
		oC1_nxt = oC1;
		sum_nxt = sum;
		rCount_nxt = rCount;
		oDone_nxt = oDone;


		case (state)
			///////////////////////////
			`IDLE: begin
				rAux1_nxt = rAux1;
				rAux2_nxt = rAux2;
				rAux3_nxt = rAux3;
				oC0_nxt = oC0;
				oC1_nxt = oC1;
				sum_nxt = sum;
				rCount_nxt = rCount;
				oDone_nxt = oDone;
			end
			///////////////////////////
			`SHIFT_V0_ADD_K2: begin
				rAux1_nxt = (oC0<<4) + iK2;
				rAux2_nxt = rAux2;
				rAux3_nxt = rAux3;
				oC0_nxt = oC0;
				oC1_nxt = oC1;
				sum_nxt = sum;
				rCount_nxt = rCount;
				oDone_nxt = oDone;
			end
			///////////////////////////
			`ADD_V0_SUM: begin
				rAux1_nxt = rAux1;
				rAux2_nxt = oC0 + sum;
				rAux3_nxt = rAux3;
				oC0_nxt = oC0;
				oC1_nxt = oC1;
				sum_nxt = sum;
				rCount_nxt = rCount;
				oDone_nxt = oDone;
			end
			///////////////////////////
			`SHIFT_V0_ADD_K3: begin
				rAux1_nxt = rAux1;
				rAux2_nxt = rAux2;
				rAux3_nxt = (oC0>>5) + iK3;
				oC0_nxt = oC0;
				oC1_nxt = oC1;
				sum_nxt = sum;
				rCount_nxt = rCount;
				oDone_nxt = oDone;
			end		
			///////////////////////////
			`XOR_ALL1: begin
				rAux1_nxt = rAux1;
				rAux2_nxt = rAux2;
				rAux3_nxt = rAux1^rAux2^rAux3;
				oC0_nxt = oC0;
				oC1_nxt = oC1;
				sum_nxt = sum;
				rCount_nxt = rCount;
				oDone_nxt = oDone;
			end
			///////////////////////////
			`SUB_ALL1: begin
				rAux1_nxt = rAux1;
				rAux2_nxt = rAux2;
				rAux3_nxt = rAux3;
				oC0_nxt = oC0;
				oC1_nxt = oC1 - rAux3;
				sum_nxt = sum;
				rCount_nxt = rCount;
				oDone_nxt = oDone;
				//$display("%x",oC0_nxt);
			end
			///////////////////////////
			`SHIFT_V1_ADD_K0: begin
				rAux1_nxt = (oC1<<4) + iK0;
				rAux2_nxt = rAux2;
				rAux3_nxt = rAux3;
				oC0_nxt = oC0;
				oC1_nxt = oC1;
				sum_nxt = sum;
				rCount_nxt = rCount;
				oDone_nxt = oDone;
			end
			///////////////////////////
			`ADD_V1_SUM: begin
				rAux1_nxt = rAux1;
				rAux2_nxt = oC1 + sum;
				rAux3_nxt = rAux3;
				oC0_nxt = oC0;
				oC1_nxt = oC1;
				sum_nxt = sum;
				rCount_nxt = rCount;
				oDone_nxt = oDone;
			end
			///////////////////////////
			`SHIFT_V1_ADD_K1: begin
				rAux1_nxt = rAux1;
				rAux2_nxt = rAux2;
				rAux3_nxt = (oC1>>5) + iK1;
				oC0_nxt = oC0;
				oC1_nxt = oC1;
				sum_nxt = sum;
				rCount_nxt = rCount;
				oDone_nxt = oDone;
			end
			///////////////////////////
			`XOR_ALL2: begin
				rAux1_nxt = rAux1;
				rAux2_nxt = rAux2;
				rAux3_nxt = rAux1^rAux2^rAux3;
				oC0_nxt = oC0;
				oC1_nxt = oC1;
				sum_nxt = sum;
				rCount_nxt = rCount;
				oDone_nxt = oDone;
			end
			///////////////////////////
			`SUB_ALL2: begin
				rAux1_nxt = rAux1;
				rAux2_nxt = rAux2;
				rAux3_nxt = rAux3;
				oC0_nxt = oC0 - rAux3;
				oC1_nxt = oC1;
				sum_nxt = sum;
				oDone_nxt = oDone;
				rCount_nxt = rCount;
			end
			///////////////////////////
			`SUB_DELTA: begin
				rAux1_nxt = rAux1;
				rAux2_nxt = rAux2;
				rAux3_nxt = rAux3;
				oC0_nxt = oC0;
				oC1_nxt = oC1;
				sum_nxt = sum - DELTA;
				rCount_nxt = rCount+1;

				if(rCount == ROUND_NUMBER-1) begin
					oDone_nxt = 1;
				end

				else begin
					oDone_nxt = oDone;
				end
			end
			//////////////////////////
			`DONE: begin
				rAux1_nxt = rAux1;
				rAux2_nxt = rAux2;
				rAux3_nxt = rAux3;
				oC0_nxt = oC0;
				oC1_nxt = oC1;
				sum_nxt = sum;
				rCount_nxt = rCount;
				oDone_nxt = oDone;
			end

		endcase
	end


	// NEXT STATE LOGIC
	always@(posedge clk) begin
		
		if(!iStart || rst) begin
			state <= `IDLE;
		end

		else begin
			state <= `IDLE;

			case(state)
				///////////////////////////
				`IDLE: begin
					if (!iStart) begin
						state <= `IDLE;
					end
					else begin
						state <= `SHIFT_V0_ADD_K2;
					end
				end
				///////////////////////////
				`SHIFT_V0_ADD_K2: begin
					state <= `ADD_V0_SUM;
				end
				///////////////////////////
				`ADD_V0_SUM: begin
					state <= `SHIFT_V0_ADD_K3;
				end
				///////////////////////////
				`SHIFT_V0_ADD_K3: begin
					state <= `XOR_ALL1;
				end
				///////////////////////////
				`XOR_ALL1: begin
					state <= `SUB_ALL1;
				end
				///////////////////////////
				`SUB_ALL1: begin
					state <= `SHIFT_V1_ADD_K0;
				end
				///////////////////////////
				`SHIFT_V1_ADD_K0: begin
					state <= `ADD_V1_SUM;
				end
				///////////////////////////
				`ADD_V1_SUM: begin
					state <= `SHIFT_V1_ADD_K1;
				end
				///////////////////////////
				`SHIFT_V1_ADD_K1: begin
					state <= `XOR_ALL2;
				end
				///////////////////////////
				`XOR_ALL2: begin
					state <= `SUB_ALL2;
				end
				///////////////////////////
				`SUB_ALL2: begin
					state <= `SUB_DELTA;
				end
				///////////////////////////
				`SUB_DELTA: begin
					state <= `DONE;
				end
				///////////////////////////
				`DONE: begin
					if(oDone) begin
						state <= `DONE;
					end
					
					else begin
						state <= `SHIFT_V0_ADD_K2;
					end
				end
				//////////////////////////
			endcase
		end
	end


	// OUTPUT LOGIC
	always @(posedge clk) begin

		if (!iStart || rst) begin
			rAux1 <= 0;
			rAux2 <= 0;
			rAux3 <= 0;
			oC0 <= iV0;
			oC1 <= iV1;
			sum <= 32'hC6EF3720;
			rCount <= 0;
			oDone <= 0;
		end
		else begin
			rAux1 <= rAux1_nxt;
			rAux2 <= rAux2_nxt;
			rAux3 <= rAux3_nxt;
			oC0 <= oC0_nxt;
			oC1 <= oC1_nxt;
			sum <= sum_nxt;
			rCount <= rCount_nxt;
			oDone <= oDone_nxt;
		end
	end

endmodule

proyectoLeon/codigo/tea/version1/tea.v
`timescale 1ns/10ps

`define IDLE 4'd0
`define ADD_DELTA 4'd1
`define SHIFT_V1_ADD_K0 4'd2
`define ADD_V1_SUM 4'd3
`define SHIFT_V1_ADD_K1 4'd4
`define XOR_ALL1 4'd5
`define ADD_ALL1 4'd6
`define SHIFT_V0_ADD_K2 4'd7
`define ADD_V0_SUM 4'd8
`define SHIFT_V0_ADD_K3 4'd9
`define XOR_ALL2 4'd10
`define ADD_ALL2 4'd11
`define DONE 4'd12

module cipher 
#(
	parameter WORD_SIZE = 32,
	parameter DELTA = 32'h9e3779b9,
	parameter ROUND_NUMBER = 32
)

(
	input wire clk,
	input wire rst,
	// Texto plano
	input wire [WORD_SIZE-1:0] iV0,
	input wire [WORD_SIZE-1:0] iV1,
	// Llave
	input wire [WORD_SIZE-1:0] iK0,
	input wire [WORD_SIZE-1:0] iK1,
	input wire [WORD_SIZE-1:0] iK2,
	input wire [WORD_SIZE-1:0] iK3,
	// Texto cifrado
	output reg [WORD_SIZE-1:0] oC0,
	output reg [WORD_SIZE-1:0] oC1,
	output reg oDone
);

	parameter ROUND_NUMBER_BITS = $clog2(ROUND_NUMBER);

	reg [3:0] state;
	//
	reg [WORD_SIZE-1:0] rAux1;
	reg [WORD_SIZE-1:0] rAux2;
	reg [WORD_SIZE-1:0] rAux3;
	reg [WORD_SIZE-1:0] sum;
	reg [ROUND_NUMBER_BITS-1:0] rCount;
	//
	reg [WORD_SIZE-1:0] rAux1_nxt;
	reg [WORD_SIZE-1:0] rAux2_nxt;
	reg [WORD_SIZE-1:0] rAux3_nxt;
	reg [WORD_SIZE-1:0] sum_nxt;
	reg [ROUND_NUMBER_BITS-1:0] rCount_nxt;
	//
	reg [WORD_SIZE-1:0] oC0_nxt;
	reg [WORD_SIZE-1:0] oC1_nxt;
	reg oDone_nxt;


	// COMBINATIONAL LOGIC
	always@(*) begin

		rAux1_nxt = rAux1;
		rAux2_nxt = rAux2;
		rAux3_nxt = rAux3;
		oC0_nxt = oC0;
		oC1_nxt = oC1;
		sum_nxt = sum;
		rCount_nxt = rCount;


		case (state)
			///////////////////////////
			`IDLE: begin
				rAux1_nxt = rAux1;
				rAux2_nxt = rAux2;
				rAux3_nxt = rAux3;
				oC0_nxt = oC0;
				oC1_nxt = oC1;
				sum_nxt = sum;
				rCount_nxt = rCount;
				oDone_nxt = oDone;
			end
			///////////////////////////
			`ADD_DELTA: begin
				rAux1_nxt = rAux1;
				rAux2_nxt = rAux2;
				rAux3_nxt = rAux3;
				oC0_nxt = oC0;
				oC1_nxt = oC1;
				sum_nxt = sum + DELTA;
				rCount_nxt = rCount;
				oDone_nxt = oDone;
			end
			///////////////////////////
			`SHIFT_V1_ADD_K0: begin
				rAux1_nxt = (oC1<<4) + iK0;
				rAux2_nxt = rAux2;
				rAux3_nxt = rAux3;
				oC0_nxt = oC0;
				oC1_nxt = oC1;
				sum_nxt = sum;
				rCount_nxt = rCount;
				oDone_nxt = oDone;
			end
			///////////////////////////
			`ADD_V1_SUM: begin
				rAux1_nxt = rAux1;
				rAux2_nxt = oC1 + sum;
				rAux3_nxt = rAux3;
				oC0_nxt = oC0;
				oC1_nxt = oC1;
				sum_nxt = sum;
				rCount_nxt = rCount;
				oDone_nxt = oDone;
			end
			///////////////////////////
			`SHIFT_V1_ADD_K1: begin
				rAux1_nxt = rAux1;
				rAux2_nxt = rAux2;
				rAux3_nxt = (oC1>>5) + iK1;
				oC0_nxt = oC0;
				oC1_nxt = oC1;
				sum_nxt = sum;
				rCount_nxt = rCount;
				oDone_nxt = oDone;
			end
			///////////////////////////
			`XOR_ALL1: begin
				rAux1_nxt = rAux1;
				rAux2_nxt = rAux2;
				rAux3_nxt = rAux1^rAux2^rAux3;
				oC0_nxt = oC0;
				oC1_nxt = oC1;
				sum_nxt = sum;
				rCount_nxt = rCount;
				oDone_nxt = oDone;
			end
			///////////////////////////
			`ADD_ALL1: begin
				rAux1_nxt = rAux1;
				rAux2_nxt = rAux2;
				rAux3_nxt = rAux3;
				oC0_nxt = oC0 + rAux3;
				oC1_nxt = oC1;
				sum_nxt = sum;
				rCount_nxt = rCount;
				oDone_nxt = oDone;
			end
			///////////////////////////
			`SHIFT_V0_ADD_K2: begin
				rAux1_nxt = (oC0<<4) + iK2;
				rAux2_nxt = rAux2;
				rAux3_nxt = rAux3;
				oC0_nxt = oC0;
				oC1_nxt = oC1;
				sum_nxt = sum;
				rCount_nxt = rCount;
				oDone_nxt = oDone;
			end
			///////////////////////////
			`ADD_V0_SUM: begin
				rAux1_nxt = rAux1;
				rAux2_nxt = oC0 + sum;
				rAux3_nxt = rAux3;
				oC0_nxt = oC0;
				oC1_nxt = oC1;
				sum_nxt = sum;
				rCount_nxt = rCount;
				oDone_nxt = oDone;
			end
			///////////////////////////
			`SHIFT_V0_ADD_K3: begin
				rAux1_nxt = rAux1;
				rAux2_nxt = rAux2;
				rAux3_nxt = (oC0>>5) + iK3;
				oC0_nxt = oC0;
				oC1_nxt = oC1;
				sum_nxt = sum;
				rCount_nxt = rCount;
				oDone_nxt = oDone;
			end
			///////////////////////////
			`XOR_ALL2: begin
				rAux1_nxt = rAux1;
				rAux2_nxt = rAux2;
				rAux3_nxt = rAux1^rAux2^rAux3;
				oC0_nxt = oC0;
				oC1_nxt = oC1;
				sum_nxt = sum;
				rCount_nxt = rCount;
				oDone_nxt = oDone;
			end
			///////////////////////////
			`ADD_ALL2: begin
				rAux1_nxt = rAux1;
				rAux2_nxt = rAux2;
				rAux3_nxt = rAux3;
				oC0_nxt = oC0;
				oC1_nxt = oC1 + rAux3;
				sum_nxt = sum;
				rCount_nxt = rCount+1;

				if(rCount == ROUND_NUMBER-1) begin
					oDone_nxt = 1;
				end

				else begin
					oDone_nxt = oDone;
				end
			end
			//////////////////////////
			`DONE: begin
				rAux1_nxt = rAux1;
				rAux2_nxt = rAux2;
				rAux3_nxt = rAux3;
				oC0_nxt = oC0;
				oC1_nxt = oC1;
				sum_nxt = sum;
				rCount_nxt = rCount;
				oDone_nxt = oDone;
			end

		endcase
	end


	// NEXT STATE LOGIC
	always@(posedge clk) begin
		
		if(rst) begin
			state <= `IDLE;
		end

		else begin
			state <= `IDLE;

			case(state)
				///////////////////////////
				`IDLE: begin
					if (rst) begin
						state <= `IDLE;
					end
					else begin
						state <= `ADD_DELTA;
					end
				end
				///////////////////////////
				`ADD_DELTA: begin
					state <= `SHIFT_V1_ADD_K0;
				end
				///////////////////////////
				`SHIFT_V1_ADD_K0: begin
					state <= `ADD_V1_SUM;
				end
				///////////////////////////
				`ADD_V1_SUM: begin
					state <= `SHIFT_V1_ADD_K1;
				end
				///////////////////////////
				`SHIFT_V1_ADD_K1: begin
					state <= `XOR_ALL1;
				end
				///////////////////////////
				`XOR_ALL1: begin
					state <= `ADD_ALL1;
				end
				///////////////////////////
				`ADD_ALL1: begin
					state <= `SHIFT_V0_ADD_K2;
				end
				///////////////////////////
				`SHIFT_V0_ADD_K2: begin
					state <= `ADD_V0_SUM;
				end
				///////////////////////////
				`ADD_V0_SUM: begin
					state <= `SHIFT_V0_ADD_K3;
				end
				///////////////////////////
				`SHIFT_V0_ADD_K3: begin
					state <= `XOR_ALL2;
				end
				///////////////////////////
				`XOR_ALL2: begin
					state <= `ADD_ALL2;
				end
				///////////////////////////
				`ADD_ALL2: begin
					state <= `DONE;
				end
				///////////////////////////
				`DONE: begin
					if(oDone) begin
						state <= `DONE;
					end
					
					else begin
						state <= `ADD_DELTA;
					end
				end
			endcase
		end
	end


	// OUTPUT LOGIC
	always @(posedge clk) begin

		if (rst) begin
			rAux1 <= 0;
			rAux2 <= 0;
			rAux3 <= 0;
			oC0 <= iV0;
			oC1 <= iV1;
			sum <= 0;
			rCount <= 0;
			oDone <= 0;
		end
		else begin
			rAux1 <= rAux1_nxt;
			rAux2 <= rAux2_nxt;
			rAux3 <= rAux3_nxt;
			oC0 <= oC0_nxt;
			oC1 <= oC1_nxt;
			sum <= sum_nxt;
			rCount <= rCount_nxt;
			oDone <= oDone_nxt;
		end
	end

endmodule

proyectoLeon/codigo/tea/decipher_tb.v
`timescale 1ns/10ps

`include "decipher.v"

module testbench;

	parameter WORD_SIZE = 32;
	parameter DELTA = 32'h9e3779b9;
	parameter ROUND_NUMBER = 32;
	////////////////////////////////////
	reg clk;
	reg rst;

	reg [WORD_SIZE-1:0] key0;
	reg [WORD_SIZE-1:0] key1;
	reg [WORD_SIZE-1:0] key2;
	reg [WORD_SIZE-1:0] key3;
	reg [WORD_SIZE-1:0] A;
	reg [WORD_SIZE-1:0] B;

	wire [WORD_SIZE-1:0] A_decipher;
	wire [WORD_SIZE-1:0] B_decipher;

	wire done;
	/////////////////////////////////////////
	cipher
	#(
		.WORD_SIZE(WORD_SIZE),
		.DELTA(DELTA),
		.ROUND_NUMBER(ROUND_NUMBER)
	)
	dut
	(
		.clk(clk),
		.rst(rst),
		.iV0(A),
		.iV1(B),
		.iK0(key0),
		.iK1(key1),
		.iK2(key2),
		.iK3(key3),
		.oC0(A_decipher),
		.oC1(B_decipher),
		.oDone(done)
	);

	initial begin

		$dumpfile("decipher.vcd");
		$dumpvars;
		clk=0;
		rst = 0;

		key0 = 32'h132acf42;
		key1 = 32'h234acb45;
		key2 = 32'h3235acbe;
		key3 = 32'h4533f235;

		A = 32'hd5db9e6a;
		B = 32'hf5509056;

		#2 rst = 1;
		#4 rst = 0;


		#4000	
		$display("Plain text = %X",{A,B});
		$display("decipher text = %X",{A_decipher,B_decipher});
		//$display("Decipher text = %X",{A_decipher, B_decipher});
		
		#1 $finish;

	end

	always #5 clk=~clk;

endmodule

proyectoLeon/codigo/tea/decipher.vcd
$date
	Tue Nov 24 21:49:56 2015
$end
$version
	Icarus Verilog
$end
$timescale
	10ps
$end
$scope module testbench $end
$var wire 32 ! A_decipher [31:0] $end
$var wire 32 " B_decipher [31:0] $end
$var wire 1 # done $end
$var reg 32 $ A [31:0] $end
$var reg 32 % B [31:0] $end
$var reg 1 & clk $end
$var reg 32 ' key0 [31:0] $end
$var reg 32 ( key1 [31:0] $end
$var reg 32 ) key2 [31:0] $end
$var reg 32 * key3 [31:0] $end
$var reg 1 + rst $end
$scope module dut $end
$var wire 1 , clk $end
$var wire 32 - iK0 [31:0] $end
$var wire 32 . iK1 [31:0] $end
$var wire 32 / iK2 [31:0] $end
$var wire 32 0 iK3 [31:0] $end
$var wire 32 1 iV0 [31:0] $end
$var wire 32 2 iV1 [31:0] $end
$var wire 1 3 rst $end
$var reg 32 4 oC0 [31:0] $end
$var reg 32 5 oC0_nxt [31:0] $end
$var reg 32 6 oC1 [31:0] $end
$var reg 32 7 oC1_nxt [31:0] $end
$var reg 1 8 oDone $end
$var reg 1 9 oDone_nxt $end
$var reg 32 : rAux1 [31:0] $end
$var reg 32 ; rAux1_nxt [31:0] $end
$var reg 32 < rAux2 [31:0] $end
$var reg 32 = rAux2_nxt [31:0] $end
$var reg 32 > rAux3 [31:0] $end
$var reg 32 ? rAux3_nxt [31:0] $end
$var reg 5 @ rCount [4:0] $end
$var reg 5 A rCount_nxt [4:0] $end
$var reg 4 B state [3:0] $end
$var reg 32 C sum [31:0] $end
$var reg 32 D sum_nxt [31:0] $end
$upscope $end
$upscope $end
$enddefinitions $end
#0
$dumpvars
bx D
bx C
bx B
bx A
bx @
bx ?
bx >
bx =
bx <
bx ;
bx :
x9
x8
bx 7
bx 6
bx 5
bx 4
03
b11110101010100001001000001010110 2
b11010101110110111001111001101010 1
b1000101001100111111001000110101 0
b110010001101011010110010111110 /
b100011010010101100101101000101 .
b10011001010101100111101000010 -
0,
0+
b1000101001100111111001000110101 *
b110010001101011010110010111110 )
b100011010010101100101101000101 (
b10011001010101100111101000010 '
0&
b11110101010100001001000001010110 %
b11010101110110111001111001101010 $
x#
bx "
bx !
$end
#200
1+
13
#500
09
b0 A
b11000110111011110011011100100000 D
b11110101010100001001000001010110 7
b11010101110110111001111001101010 5
b0 ?
b0 =
b0 ;
b0 B
08
0#
b0 @
b11000110111011110011011100100000 C
b11110101010100001001000001010110 6
b11110101010100001001000001010110 "
b11010101110110111001111001101010 4
b11010101110110111001111001101010 !
b0 >
b0 <
b0 :
1&
1,
#600
0+
03
#1000
0&
0,
#1500
b10001111111011111001001101011110 ;
b1 B
1&
1,
#2000
0&
0,
#2500
b10011100110010101101010110001010 =
b10 B
b10001111111011111001001101011110 :
1&
1,
#3000
0&
0,
#3500
b1001011111000101100111100101000 ?
b10011100110010101101010110001010 <
b11 B
1&
1,
#4000
0&
0,
#4500
b1011000110001111000100111111100 ?
b100 B
b1001011111000101100111100101000 >
1&
1,
#5000
0&
0,
#5500
b10011100100010010000011001011010 7
b1011000110001111000100111111100 >
b101 B
1&
1,
#6000
0&
0,
#6500
b11011011101110110011010011100010 ;
b110 B
b10011100100010010000011001011010 6
b10011100100010010000011001011010 "
1&
1,
#7000
0&
0,
#7500
b1100011011110000011110101111010 =
b11011011101110110011010011100010 :
b111 B
1&
1,
#8000
0&
0,
#8500
b101000001011110001001101110111 ?
b1000 B
b1100011011110000011110101111010 <
1&
1,
#9000
0&
0,
#9500
b10010000111011000001101011101111 ?
b101000001011110001001101110111 >
b1001 B
1&
1,
#10000
0&
0,
#10500
b1000100111011111000001101111011 5
b1010 B
b10010000111011000001101011101111 >
1&
1,
#11000
0&
0,
#11500
b1 A
b101000101101111011110101100111 D
b1000100111011111000001101111011 4
b1000100111011111000001101111011 !
b1011 B
1&
1,
#12000
0&
0,
#12500
b1100 B
b1 @
b101000101101111011110101100111 C
1&
1,
#13000
0&
0,
#13500
b10000001001011011110010001101110 ;
b1 B
1&
1,
#14000
0&
0,
#14500
b1101101101001110100000011100010 =
b10 B
b10000001001011011110010001101110 :
1&
1,
#15000
0&
0,
#15500
b1000111010110110110111001010000 ?
b1101101101001110100000011100010 <
b11 B
1&
1,
#16000
0&
0,
#16500
b10101011110100011100101011011100 ?
b100 B
b1000111010110110110111001010000 >
1&
1,
#17000
0&
0,
#17500
b11110000101101110011101101111110 7
b10101011110100011100101011011100 >
b101 B
1&
1,
#18000
0&
0,
#18500
b11110100111101000011100100010 ;
b110 B
b11110000101101110011101101111110 6
b11110000101101110011101101111110 "
1&
1,
#19000
0&
0,
#19500
b11001011011101111100011100101 =
b11110100111101000011100100010 :
b111 B
1&
1,
#20000
0&
0,
#20500
b101010110100001000010100100000 ?
b1000 B
b11001011011101111100011100101 <
1&
1,
#21000
0&
0,
#21500
b101101001000001111101011100111 ?
b101010110100001000010100100000 >
b1001 B
1&
1,
#22000
0&
0,
#22500
b10111110011101000100010010100 5
b1010 B
b101101001000001111101011100111 >
1&
1,
#23000
0&
0,
#23500
b10 A
b10001010100000000100001110101110 D
b10111110011101000100010010100 4
b10111110011101000100010010100 !
b1011 B
1&
1,
#24000
0&
0,
#24500
b1100 B
b10 @
b10001010100000000100001110101110 C
1&
1,
#25000
0&
0,
#25500
b10101111000111100011010111111110 ;
b1 B
1&
1,
#26000
0&
0,
#26500
b10100010010011101100110001000010 =
b10 B
b10101111000111100011010111111110 :
1&
1,
#27000
0&
0,
#27500
b1000101111100100110011001111001 ?
b10100010010011101100110001000010 <
b11 B
1&
1,
#28000
0&
0,
#28500
b1001000101000101001111111000101 ?
b100 B
b1000101111100100110011001111001 >
1&
1,
#29000
0&
0,
#29500
b10101000000101001001101110111001 7
b1001000101000101001111111000101 >
b101 B
1&
1,
#30000
0&
0,
#30500
b10010100011101001000101011010010 ;
b110 B
b10101000000101001001101110111001 6
b10101000000101001001101110111001 "
1&
1,
#31000
0&
0,
#31500
b110010100101001101111101100111 =
b10010100011101001000101011010010 :
b111 B
1&
1,
#32000
0&
0,
#32500
b101000100010110111000000100010 ?
b1000 B
b110010100101001101111101100111 <
1&
1,
#33000
0&
0,
#33500
b10001110011010110010010110010111 ?
b101000100010110111000000100010 >
b1001 B
1&
1,
#34000
0&
0,
#34500
b10001001011000110110001011111101 5
b1010 B
b10001110011010110010010110010111 >
1&
1,
#35000
0&
0,
#35500
b11 A
b11101100010010001100100111110101 D
b10001001011000110110001011111101 4
b10001001011000110110001011111101 !
b1011 B
1&
1,
#36000
0&
0,
#36500
b1100 B
b11 @
b11101100010010001100100111110101 C
1&
1,
#37000
0&
0,
#37500
b11001000011010111101110010001110 ;
b1 B
1&
1,
#38000
0&
0,
#38500
b1110101101011000010110011110010 =
b10 B
b11001000011010111101110010001110 :
1&
1,
#39000
0&
0,
#39500
b1001001011111110000110101001100 ?
b1110101101011000010110011110010 <
b11 B
1&
1,
#40000
0&
0,
#40500
b11110100101110001111110100110000 ?
b100 B
b1001001011111110000110101001100 >
1&
1,
#41000
0&
0,
#41500
b10110011010110111001111010001001 7
b11110100101110001111110100110000 >
b101 B
1&
1,
#42000
0&
0,
#42500
b1001000111001001011011111010010 ;
b110 B
b10110011010110111001111010001001 6
b10110011010110111001111010001001 "
1&
1,
#43000
0&
0,
#43500
b10011111101001000110100001111110 =
b1001000111001001011011111010010 :
b111 B
1&
1,
#44000
0&
0,
#44500
b101000111001011010100000111001 ?
b1000 B
b10011111101001000110100001111110 <
1&
1,
#45000
0&
0,
#45500
b11111111101001010111011110010101 ?
b101000111001011010100000111001 >
b1001 B
1&
1,
#46000
0&
0,
#46500
b10001001101111011110101101101000 5
b1010 B
b11111111101001010111011110010101 >
1&
1,
#47000
0&
0,
#47500
b100 A
b1001110000100010101000000111100 D
b10001001101111011110101101101000 4
b10001001101111011110101101101000 !
b1011 B
1&
1,
#48000
0&
0,
#48500
b1100 B
b100 @
b1001110000100010101000000111100 C
1&
1,
#49000
0&
0,
#49500
b11001110000101000110001100111110 ;
b1 B
1&
1,
#50000
0&
0,
#50500
b11010111110011110011101110100100 =
b10 B
b11001110000101000110001100111110 :
1&
1,
#51000
0&
0,
#51500
b1001001100000011110000110010000 ?
b11010111110011110011101110100100 <
b11 B
1&
1,
#52000
0&
0,
#52500
b1010000010110101011100100001010 ?
b100 B
b1001001100000011110000110010000 >
1&
1,
#53000
0&
0,
#53500
b1100011000000001110010101111111 7
b1010000010110101011100100001010 >
b101 B
1&
1,
#54000
0&
0,
#54500
b1000011001110010010011100110010 ;
b110 B
b1100011000000001110010101111111 6
b1100011000000001110010101111111 "
1&
1,
#55000
0&
0,
#55500
b10110001000100100011010110111011 =
b1000011001110010010011100110010 :
b111 B
1&
1,
#56000
0&
0,
#56500
b100110011000101101001001110000 ?
b1000 B
b10110001000100100011010110111011 <
1&
1,
#57000
0&
0,
#57500
b11010100010010011100000011111001 ?
b100110011000101101001001110000 >
b1001 B
1&
1,
#58000
0&
0,
#58500
b10110101011101000010101001101111 5
b1010 B
b11010100010010011100000011111001 >
1&
1,
#59000
0&
0,
#59500
b101 A
b10101111110110011101011010000011 D
b10110101011101000010101001101111 4
b10110101011101000010101001101111 !
b1011 B
1&
1,
#60000
0&
0,
#60500
b1100 B
b101 @
b10101111110110011101011010000011 C
1&
1,
#61000
0&
0,
#61500
b10001001011110000101001110101110 ;
b1 B
1&
1,
#62000
0&
0,
#62500
b1100101010011100000000011110010 =
b10 B
b10001001011110000101001110101110 :
1&
1,
#63000
0&
0,
#63500
b1001010110111111001001110001000 ?
b1100101010011100000000011110010 <
b11 B
1&
1,
#64000
0&
0,
#64500
b10100110111010011100000011010100 ?
b100 B
b1001010110111111001001110001000 >
1&
1,
#65000
0&
0,
#65500
b10111100000101110010010010101011 7
b10100110111010011100000011010100 >
b101 B
1&
1,
#66000
0&
0,
#66500
b11010100100111010001100111110010 ;
b110 B
b10111100000101110010010010101011 6
b10111100000101110010010010101011 "
1&
1,
#67000
0&
0,
#67500
b1101011111100001111101100101110 =
b11010100100111010001100111110010 :
b111 B
1&
1,
#68000
0&
0,
#68500
b101001001010111000010001101010 ?
b1000 B
b1101011111100001111101100101110 <
1&
1,
#69000
0&
0,
#69500
b10010110010001100110011010110110 ?
b101001001010111000010001101010 >
b1001 B
1&
1,
#70000
0&
0,
#70500
b11111001011011100001110111001 5
b1010 B
b10010110010001100110011010110110 >
1&
1,
#71000
0&
0,
#71500
b110 A
b10001101000100101110011001010 D
b11111001011011100001110111001 4
b11111001011011100001110111001 !
b1011 B
1&
1,
#72000
0&
0,
#72500
b1100 B
b110 @
b10001101000100101110011001010 C
1&
1,
#73000
0&
0,
#73500
b100101000100011110100001001110 ;
b1 B
1&
1,
#74000
0&
0,
#74500
b110000110100000010000010000011 =
b10 B
b100101000100011110100001001110 :
1&
1,
#75000
0&
0,
#75500
b1000110001011010110000001010010 ?
b110000110100000010000010000011 <
b11 B
1&
1,
#76000
0&
0,
#76500
b1010011111011001010100010011111 ?
b100 B
b1000110001011010110000001010010 >
1&
1,
#77000
0&
0,
#77500
b1101000001010100111110000001100 7
b1010011111011001010100010011111 >
b101 B
1&
1,
#78000
0&
0,
#78500
b10010101110100101001000000000010 ;
b110 B
b1101000001010100111110000001100 6
b1101000001010100111110000001100 "
1&
1,
#79000
0&
0,
#79500
b1111001110011001101100011010110 =
b10010101110100101001000000000010 :
b111 B
1&
1,
#80000
0&
0,
#80500
b100110100011000001111100100101 ?
b1000 B
b1111001110011001101100011010110 <
1&
1,
#81000
0&
0,
#81500
b11001010100100100101011111110001 ?
b100110100011000001111100100101 >
b1001 B
1&
1,
#82000
0&
0,
#82500
b1010100100110110110101111001000 5
b1010 B
b11001010100100100101011111110001 >
1&
1,
#83000
0&
0,
